RLFramework/__init__.py
RLFramework/deeprl/Agent.py
RLFramework/deeprl/Environment.py
RLFramework/deeprl/__init__.py
RLFramework/exp/__init__.py
RLFramework/exp/epsilon_greedy.py
RLFramework/exp/exploration.py
RLFramework/exp/gaussian.py
RLFramework/exp/stochastic_discrete.py
RLFramework/gym/__init__.py
RLFramework/gym/gymnasium_environment.py
RLFramework/net/__init__.py
RLFramework/net/network.py
RLFramework/net/policy_net.py
RLFramework/net/q_net.py
RLFramework/net/value_net.py
RLFramework/optim/__init__.py
RLFramework/optim/optimizer.py
RLFramework/optim/policy_optimizer.py
RLFramework/optim/q_optimizer.py
RLFramework/optim/value_optimizer.py
RLFramework/optim/policy_optims/__init__.py
RLFramework/optim/policy_optims/clipped_surrogate_policy_optim.py
RLFramework/optim/policy_optims/dkl_policy_optim.py
RLFramework/optim/q_optims/__init__.py
RLFramework/optim/q_optims/target_q_optim.py
RLFramework/optim/q_optims/target_v_2q_optim.py
RLFramework/optim/value_optims/__init__.py
RLFramework/optim/value_optims/self_value_optim.py
RLFramework/optim/value_optims/soft_value_optim.py
RLFramework/optim/value_optims/target_value_optim.py
RLFramework/space/__init__.py
RLFramework/space/continuous.py
RLFramework/space/discrete.py
RLFramework/space/space.py
RLFramework/trainer/Trainer.py
RLFramework/trainer/__init__.py
RLFramework/traj/__init__.py
RLFramework/traj/contiguous_sample.py
RLFramework/traj/replay_memory.py
RLFramework/traj/sample.py
RLFramework/traj/sample_iterator.py
RLFramework/traj/trajectory.py
RLFramework/traj/trajectory_element.py
RLFramework/traj/volatile_memory.py
RLFramework/utils/__init__.py
RLFramework/utils/logger.py
RLFramework/wrapper/__init__.py
RLFramework/wrapper/array.py
RLFramework/wrapper/tensor.py
RLFramework/wrapper/wrapper.py
RLFramework-0.10.0.dist-info/METADATA
RLFramework-0.10.0.dist-info/WHEEL
RLFramework-0.10.0.dist-info/top_level.txt
RLFramework-0.10.0.dist-info/RECORD
